{
    "wordLet": [
      {
        "word": "Penguin",
        "hint": "A type of bird"
      },
      {
        "word": "Umbrella",
        "hint": "A weather-related object"
      },
      {
        "word": "Volcano",
        "hint": "A natural landform"
      },
      {
        "word": "Puzzle",
        "hint": "A form of entertainment or challenge"
      },
      {
        "word": "Sapphire",
        "hint": "A type of gemstone"
      },
      {
        "word": "Oasis",
        "hint": "A natural feature found in dry places"
      },
      {
        "word": "Whistle",
        "hint": "A type of sound or tool"
      },
      {
        "word": "Igloo",
        "hint": "A type of dwelling"
      },
      {
        "word": "Lighthouse",
        "hint": "A structure used for navigation"
      },
      {
        "word": "Scorpion",
        "hint": "A desert-dwelling animal"
      },
      {
        "word": "Banana",
        "hint": "A type of fruit"
      },
      {
        "word": "Telescope",
        "hint": "A tool used for seeing faraway things"
      },
      {
        "word": "Cactus",
        "hint": "A type of plant"
      },
      {
        "word": "Eclipse",
        "hint": "A rare celestial event"
      },
      {
        "word": "Lantern",
        "hint": "A portable light source"
      },
      {
        "word": "Parrot",
        "hint": "A type of bird"
      },
      {
        "word": "Trampoline",
        "hint": "A piece of recreational equipment"
      },
      {
        "word": "Castle",
        "hint": "A structure associated with royalty"
      },
      {
        "word": "Butterfly",
        "hint": "An insect"
      },
      {
        "word": "Submarine",
        "hint": "A type of vehicle used underwater"
      }
    ]
  }
  
